aimhii/__about__.py
aimhii/__init__.py
aimhii/extract_chimeras.py
aimhii/filter_bam.py
aimhii/find_insert_clusters.py
aimhii/make_random_sequence.py
aimhii/make_synthetic_insertion.py
aimhii/plot_metaclusters.py
aimhii-0.5.5.dist-info/DESCRIPTION.rst
aimhii-0.5.5.dist-info/entry_points.txt
aimhii-0.5.5.dist-info/METADATA
aimhii-0.5.5.dist-info/metadata.json
aimhii-0.5.5.dist-info/RECORD
aimhii-0.5.5.dist-info/top_level.txt
aimhii-0.5.5.dist-info/WHEEL
