Metadata-Version: 2.0
Name: aimhii
Version: 0.5.5
Summary: A pipeline for mapping insertion mutants from whole genome shotgun data
Home-page: https://github.com/granek/aimhii/
Author: Josh Granek
Author-email: joshua.granek@duke.edu
License: The MIT License (MIT)
Platform: UNKNOWN
Classifier: Development Status :: 4 - Beta
Classifier: Intended Audience :: Developers
Classifier: Intended Audience :: Science/Research
Classifier: Topic :: Scientific/Engineering :: Bio-Informatics
Classifier: License :: OSI Approved :: MIT License
Classifier: Programming Language :: Python :: 2
Classifier: Programming Language :: Python :: 2.7
Requires-Dist: numpy (>=1.8.1)
Requires-Dist: biopython (>=1.64)
Requires-Dist: matplotlib (>=1.3.1)
Requires-Dist: pysam (>=0.9.0)
Requires-Dist: HTSeq (>=0.6.1)
